hescorehpxml/__init__.py
hescorehpxml/__main__.py
hescorehpxml/base.py
hescorehpxml/create_all_example_json.py
hescorehpxml/exceptions.py
hescorehpxml/hpxml2.py
hescorehpxml/hpxml3.py
hescorehpxml/lookups/lu_ceiling_eff_rvalue.csv
hescorehpxml/lookups/lu_floor_eff_rvalue.csv
hescorehpxml/lookups/lu_knee_wall_eff_rvalue.csv
hescorehpxml/lookups/lu_roof_eff_rvalue.csv
hescorehpxml/lookups/lu_wall_eff_rvalue.csv
hescorehpxml/schemas/hescore_json.schema.json
hescorehpxml/schemas/hpxml-2.3.0/BaseElements.xsd
hescorehpxml/schemas/hpxml-2.3.0/HPXML.xsd
hescorehpxml/schemas/hpxml-2.3.0/HPXMLDataTypes.xsd
hescorehpxml/schemas/hpxml-3.0.0/BaseElements.xsd
hescorehpxml/schemas/hpxml-3.0.0/HPXML.xsd
hescorehpxml/schemas/hpxml-3.0.0/HPXMLDataTypes.xsd
hescore_hpxml-7.0.2.dist-info/LICENSE
hescore_hpxml-7.0.2.dist-info/METADATA
hescore_hpxml-7.0.2.dist-info/WHEEL
hescore_hpxml-7.0.2.dist-info/entry_points.txt
hescore_hpxml-7.0.2.dist-info/top_level.txt
hescore_hpxml-7.0.2.dist-info/RECORD
